LICENSE.txt
MANIFEST.in
README.rst
changelog.txt
pyproject.toml
setup.py
PilLite/Image.py
PilLite/__about__.py
PilLite/__init__.py
Pil_Lite.egg-info/PKG-INFO
Pil_Lite.egg-info/SOURCES.txt
Pil_Lite.egg-info/dependency_links.txt
Pil_Lite.egg-info/requires.txt
Pil_Lite.egg-info/top_level.txt
src/lib.c
src/lib.h
src/py_ext_build.py
src/stb/stb_image.c
src/stb/stb_image.h
src/stb/stb_image_resize2.c
src/stb/stb_image_resize2.h
src/stb/stb_image_write.c
src/stb/stb_image_write.h
test/test_basic.py
test/test_drawing.py
test/test_numpy.py
test/data/image.bmp
test/data/image.jpg
test/data/image.png
test/data/image.tga
test/data/image.tif