Metadata-Version: 2.1
Name: Pil-Lite
Version: 0.1.3
Summary: Python Imaging Library Lite
Author-email: Alexey Vasilyev <alexey@alexadotlife.com>
License: MIT
Project-URL: Homepage, https://github.com/alexa-infra/pil-lite
Project-URL: Issues, https://github.com/alexa-infra/pil-lite/issues
Classifier: Programming Language :: Python :: 3
Classifier: Programming Language :: Python :: Implementation :: CPython
Classifier: Programming Language :: Python :: Implementation :: PyPy
Classifier: License :: OSI Approved :: MIT License
Classifier: Development Status :: 4 - Beta
Classifier: Topic :: Utilities
Classifier: Topic :: Multimedia :: Graphics
Classifier: Topic :: Multimedia :: Graphics :: Graphics Conversion
Requires-Python: >=3.8
License-File: LICENSE.txt
Requires-Dist: cffi>=1.1
Provides-Extra: tests
Requires-Dist: pytest; extra == "tests"
